wtu/__init__.py
wtu/health_report/__init__.py
wtu-1.0.1.dist-info/METADATA
wtu-1.0.1.dist-info/WHEEL
wtu-1.0.1.dist-info/top_level.txt
wtu-1.0.1.dist-info/RECORD
