Metadata-Version: 2.1
Name: wtu
Version: 1.0.1
Summary: WTU gadget
Home-page: UNKNOWN
Author: Syaoran
Author-email: SyaoranCheung@outlook.com
License: MIT License
Platform: UNKNOWN
Classifier: Programming Language :: Python :: 3
Classifier: License :: OSI Approved :: MIT License
Classifier: Operating System :: OS Independent
Requires-Dist: httpx
Requires-Dist: schedule
